README.txt
setup.py
vpnotebook/__init__.py
vpnotebook.egg-info/PKG-INFO
vpnotebook.egg-info/SOURCES.txt
vpnotebook.egg-info/dependency_links.txt
vpnotebook.egg-info/top_level.txt
vpnotebook/data/kernel.json