Metadata-Version: 1.1
Name: vpnotebook
Version: 0.1.2
Summary: pip installable VPython kernel for Jupyter Notebook
Home-page: http://pypi.python.org/pypi/vpnotebook/
Author: Bruce Sherwood, John Coady, Ruth Chabay
Author-email: johncoady@shaw.ca
License: New BSD License
Keywords: vpython kernel
Platform: UNKNOWN
Classifier: Framework :: IPython
Classifier: Development Status :: 3 - Alpha
Classifier: Environment :: Web Environment
Classifier: Intended Audience :: End Users/Desktop
Classifier: Natural Language :: English
Classifier: Programming Language :: Python
